{
 "result":"success",
 "documentation":"https://www.exchangerate-api.com/docs",
 "terms_of_use":"https://www.exchangerate-api.com/terms",
 "time_last_update_unix":1696118402,
 "time_last_update_utc":"Sun, 01 Oct 2023 00:00:02 +0000",
 "time_next_update_unix":1696204802,
 "time_next_update_utc":"Mon, 02 Oct 2023 00:00:02 +0000",
 "base_code":"KES",
 "conversion_rates":{
  "KES":1,
  "AED":0.02479,
  "AFN":0.5285,
  "ALL":0.6815,
  "AMD":2.6217,
  "ANG":0.01208,
  "AOA":5.5852,
  "ARS":2.3626,
  "AUD":0.01050,
  "AWG":0.01208,
  "AZN":0.01149,
  "BAM":0.01254,
  "BBD":0.01350,
  "BDT":0.7455,
  "BGN":0.01254,
  "BHD":0.002538,
  "BIF":19.1534,
  "BMD":0.006750,
  "BND":0.009230,
  "BOB":0.04685,
  "BRL":0.03350,
  "BSD":0.006750,
  "BTN":0.5613,
  "BWP":0.09299,
  "BYN":0.02062,
  "BZD":0.01350,
  "CAD":0.009110,
  "CDF":16.5832,
  "CHF":0.006180,
  "CLP":6.1261,
  "CNY":0.04933,
  "COP":27.5818,
  "CRC":3.6308,
  "CUP":0.1620,
  "CVE":0.7067,
  "CZK":0.1540,
  "DJF":1.1996,
  "DKK":0.04782,
  "DOP":0.3837,
  "DZD":0.9295,
  "EGP":0.2089,
  "ERN":0.1012,
  "ETB":0.3740,
  "EUR":0.006409,
  "FJD":0.01531,
  "FKP":0.005543,
  "FOK":0.04782,
  "GBP":0.005543,
  "GEL":0.01808,
  "GGP":0.005543,
  "GHS":0.07844,
  "GIP":0.005543,
  "GMD":0.4421,
  "GNF":58.0390,
  "GTQ":0.05315,
  "GYD":1.4147,
  "HKD":0.05286,
  "HNL":0.1668,
  "HRK":0.04829,
  "HTG":0.9159,
  "HUF":2.4626,
  "IDR":104.7549,
  "ILS":0.02549,
  "IMP":0.005543,
  "INR":0.5613,
  "IQD":8.8555,
  "IRR":288.9324,
  "ISK":0.9297,
  "JEP":0.005543,
  "JMD":1.0457,
  "JOD":0.004786,
  "JPY":1.0084,
  "KGS":0.6003,
  "KHR":27.8475,
  "KID":0.01050,
  "KMF":3.1532,
  "KRW":9.1357,
  "KWD":0.002090,
  "KYD":0.005625,
  "KZT":3.2432,
  "LAK":137.4986,
  "LBP":101.2495,
  "LKR":2.1879,
  "LRD":1.2847,
  "LSL":0.1283,
  "LYD":0.03305,
  "MAD":0.06959,
  "MDL":0.1225,
  "MGA":30.7379,
  "MKD":0.3924,
  "MMK":14.2054,
  "MNT":23.4870,
  "MOP":0.05445,
  "MRU":0.2588,
  "MUR":0.3014,
  "MVR":0.1044,
  "MWK":7.4638,
  "MXN":0.1166,
  "MYR":0.03182,
  "MZN":0.4290,
  "NAD":0.1283,
  "NGN":5.2505,
  "NIO":0.2475,
  "NOK":0.07241,
  "NPR":0.8981,
  "NZD":0.01114,
  "OMR":0.002595,
  "PAB":0.006750,
  "PEN":0.02564,
  "PGK":0.02462,
  "PHP":0.3848,
  "PKR":1.9431,
  "PLN":0.02954,
  "PYG":49.4072,
  "QAR":0.02457,
  "RON":0.03143,
  "RSD":0.7506,
  "RUB":0.6506,
  "RWF":8.1666,
  "SAR":0.02531,
  "SBD":0.05714,
  "SCR":0.09182,
  "SDG":4.0432,
  "SEK":0.07385,
  "SGD":0.009230,
  "SHP":0.005543,
  "SLE":0.1392,
  "SLL":139.2111,
  "SOS":3.8638,
  "SRD":0.2607,
  "SSP":6.7662,
  "STN":0.1570,
  "SYP":87.7023,
  "SZL":0.1283,
  "THB":0.2442,
  "TJS":0.07425,
  "TMT":0.02364,
  "TND":0.02146,
  "TOP":0.01612,
  "TRY":0.1833,
  "TTD":0.04587,
  "TVD":0.01050,
  "TWD":0.2180,
  "TZS":16.9026,
  "UAH":0.2490,
  "UGX":25.3879,
  "USD":0.006750,
  "UYU":0.2590,
  "UZS":82.7990,
  "VES":0.2324,
  "VND":163.5538,
  "VUV":0.8295,
  "WST":0.01877,
  "XAF":4.2043,
  "XCD":0.01822,
  "XDR":0.005125,
  "XOF":4.2043,
  "XPF":0.7648,
  "YER":1.6915,
  "ZAR":0.1283,
  "ZMW":0.1400,
  "ZWL":35.5501
 }
}