{
 "result":"success",
 "documentation":"https://www.exchangerate-api.com/docs",
 "terms_of_use":"https://www.exchangerate-api.com/terms",
 "time_last_update_unix":1650844802,
 "time_last_update_utc":"Mon, 25 Apr 2022 00:00:02 +0000",
 "time_next_update_unix":1650931202,
 "time_next_update_utc":"Tue, 26 Apr 2022 00:00:02 +0000",
 "base_code":"KES",
 "conversion_rates":{
  "KES":1,
  "AED":0.03176,
  "AFN":0.7574,
  "ALL":0.9601,
  "AMD":4.0683,
  "ANG":0.01548,
  "AOA":3.4969,
  "ARS":0.9867,
  "AUD":0.01184,
  "AWG":0.01548,
  "AZN":0.01469,
  "BAM":0.01562,
  "BBD":0.01730,
  "BDT":0.7482,
  "BGN":0.01562,
  "BHD":0.003252,
  "BIF":17.7639,
  "BMD":0.008648,
  "BND":0.01182,
  "BOB":0.05962,
  "BRL":0.04072,
  "BSD":0.008648,
  "BTN":0.6608,
  "BWP":0.1011,
  "BYN":0.02859,
  "BZD":0.01730,
  "CAD":0.01094,
  "CDF":17.3026,
  "CHF":0.008256,
  "CLP":7.1267,
  "CNY":0.05624,
  "COP":32.6076,
  "CRC":5.6650,
  "CUP":0.2075,
  "CVE":0.8808,
  "CZK":0.1944,
  "DJF":1.5369,
  "DKK":0.05960,
  "DOP":0.4779,
  "DZD":1.2466,
  "EGP":0.1605,
  "ERN":0.1297,
  "ETB":0.4442,
  "EUR":0.007988,
  "FJD":0.01834,
  "FKP":0.006699,
  "FOK":0.05960,
  "GBP":0.006699,
  "GEL":0.02609,
  "GGP":0.006699,
  "GHS":0.06650,
  "GIP":0.006699,
  "GMD":0.4680,
  "GNF":77.0603,
  "GTQ":0.06648,
  "GYD":1.8106,
  "HKD":0.06782,
  "HNL":0.2132,
  "HRK":0.06019,
  "HTG":0.9432,
  "HUF":2.9602,
  "IDR":124.9134,
  "ILS":0.02821,
  "IMP":0.006699,
  "INR":0.6608,
  "IQD":12.6290,
  "IRR":363.3922,
  "ISK":1.1133,
  "JEP":0.006699,
  "JMD":1.3433,
  "JOD":0.006131,
  "JPY":1.1094,
  "KGS":0.6967,
  "KHR":35.0009,
  "KID":0.01184,
  "KMF":3.9300,
  "KRW":10.7592,
  "KWD":0.002591,
  "KYD":0.007206,
  "KZT":3.8460,
  "LAK":103.8613,
  "LBP":13.0365,
  "LKR":2.8942,
  "LRD":1.3145,
  "LSL":0.1344,
  "LYD":0.04081,
  "MAD":0.08375,
  "MDL":0.1605,
  "MGA":35.0009,
  "MKD":0.4932,
  "MMK":16.0791,
  "MNT":26.4379,
  "MOP":0.06985,
  "MRU":0.3155,
  "MUR":0.3717,
  "MVR":0.1331,
  "MWK":7.0570,
  "MXN":0.1758,
  "MYR":0.03745,
  "MZN":0.5569,
  "NAD":0.1344,
  "NGN":3.5924,
  "NIO":0.3111,
  "NOK":0.07684,
  "NPR":1.0573,
  "NZD":0.01295,
  "OMR":0.003325,
  "PAB":0.008648,
  "PEN":0.03231,
  "PGK":0.03046,
  "PHP":0.4541,
  "PKR":1.6110,
  "PLN":0.03705,
  "PYG":59.5988,
  "QAR":0.03148,
  "RON":0.03953,
  "RSD":0.9419,
  "RUB":0.6780,
  "RWF":8.9559,
  "SAR":0.03243,
  "SBD":0.06989,
  "SCR":0.1244,
  "SDG":3.8513,
  "SEK":0.08209,
  "SGD":0.01182,
  "SHP":0.006699,
  "SLL":107.1272,
  "SOS":5.0062,
  "SRD":0.1796,
  "SSP":3.6626,
  "STN":0.1957,
  "SYP":21.7372,
  "SZL":0.1344,
  "THB":0.2936,
  "TJS":0.1082,
  "TMT":0.03022,
  "TND":0.02552,
  "TOP":0.01961,
  "TRY":0.1275,
  "TTD":0.05892,
  "TVD":0.01184,
  "TWD":0.2533,
  "TZS":20.0233,
  "UAH":0.2543,
  "UGX":30.4007,
  "USD":0.008648,
  "UYU":0.3576,
  "UZS":97.5421,
  "VES":0.03836,
  "VND":198.2100,
  "VUV":0.9762,
  "WST":0.02252,
  "XAF":5.2400,
  "XCD":0.02335,
  "XDR":0.006363,
  "XOF":5.2400,
  "XPF":0.9533,
  "YER":2.1639,
  "ZAR":0.1344,
  "ZMW":0.1471,
  "ZWL":1.3006
 }
}