{
 "result":"success",
 "documentation":"https://www.exchangerate-api.com/docs",
 "terms_of_use":"https://www.exchangerate-api.com/terms",
 "time_last_update_unix":1654732802,
 "time_last_update_utc":"Thu, 09 Jun 2022 00:00:02 +0000",
 "time_next_update_unix":1654819202,
 "time_next_update_utc":"Fri, 10 Jun 2022 00:00:02 +0000",
 "base_code":"USD",
 "conversion_rates":{
  "USD":1,
  "AED":3.6725,
  "AFN":88.5260,
  "ALL":111.7847,
  "AMD":433.4999,
  "ANG":1.7900,
  "AOA":428.3255,
  "ARS":121.0860,
  "AUD":1.3889,
  "AWG":1.7900,
  "AZN":1.6942,
  "BAM":1.8248,
  "BBD":2.0000,
  "BDT":92.2467,
  "BGN":1.8244,
  "BHD":0.3760,
  "BIF":2043.8355,
  "BMD":1.0000,
  "BND":1.3758,
  "BOB":6.8570,
  "BRL":4.8765,
  "BSD":1.0000,
  "BTN":77.6128,
  "BWP":11.9696,
  "BYN":2.9609,
  "BZD":2.0000,
  "CAD":1.2540,
  "CDF":1993.7497,
  "CHF":0.9774,
  "CLP":825.6399,
  "CNY":6.6862,
  "COP":3773.7160,
  "CRC":681.8846,
  "CUP":24.0000,
  "CVE":102.8803,
  "CZK":23.0655,
  "DJF":177.7210,
  "DKK":6.9607,
  "DOP":54.9368,
  "DZD":145.3460,
  "EGP":18.6474,
  "ERN":15.0000,
  "ETB":51.8549,
  "EUR":0.9331,
  "FJD":2.1538,
  "FKP":0.7973,
  "FOK":6.9607,
  "GBP":0.7973,
  "GEL":2.9475,
  "GGP":0.7973,
  "GHS":8.0184,
  "GIP":0.7973,
  "GMD":53.9763,
  "GNF":8832.4842,
  "GTQ":7.6814,
  "GYD":208.6549,
  "HKD":7.8506,
  "HNL":24.4866,
  "HRK":7.0299,
  "HTG":112.9634,
  "HUF":366.6362,
  "IDR":14424.0557,
  "ILS":3.3422,
  "IMP":0.7973,
  "INR":77.6145,
  "IQD":1455.5405,
  "IRR":41911.3528,
  "ISK":129.5969,
  "JEP":0.7973,
  "JMD":153.4051,
  "JOD":0.7090,
  "JPY":134.1087,
  "KES":117.2434,
  "KGS":79.9191,
  "KHR":4048.2219,
  "KID":1.3887,
  "KMF":459.0196,
  "KRW":1255.2898,
  "KWD":0.2996,
  "KYD":0.8333,
  "KZT":433.0250,
  "LAK":15352.9099,
  "LBP":1507.5000,
  "LKR":355.6752,
  "LRD":151.5016,
  "LSL":15.3013,
  "LYD":4.7711,
  "MAD":9.6827,
  "MDL":19.0032,
  "MGA":4007.8958,
  "MKD":57.6104,
  "MMK":1837.7597,
  "MNT":3122.6606,
  "MOP":8.0862,
  "MRU":36.4133,
  "MUR":43.6507,
  "MVR":15.3640,
  "MWK":1024.8459,
  "MXN":19.5918,
  "MYR":4.3837,
  "MZN":64.2135,
  "NAD":15.3013,
  "NGN":414.1204,
  "NIO":35.7248,
  "NOK":9.4660,
  "NPR":124.1805,
  "NZD":1.5504,
  "OMR":0.3845,
  "PAB":1.0000,
  "PEN":3.7506,
  "PGK":3.5458,
  "PHP":52.9514,
  "PKR":201.2472,
  "PLN":4.2695,
  "PYG":6838.7481,
  "QAR":3.6400,
  "RON":4.6114,
  "RSD":109.4134,
  "RUB":60.2401,
  "RWF":1040.4697,
  "SAR":3.7500,
  "SBD":7.9585,
  "SCR":13.1009,
  "SDG":445.3014,
  "SEK":9.8082,
  "SGD":1.3758,
  "SHP":0.7973,
  "SLL":13073.1570,
  "SOS":576.9905,
  "SRD":21.6452,
  "SSP":474.3512,
  "STN":22.8592,
  "SYP":2511.8134,
  "SZL":15.3013,
  "THB":34.5227,
  "TJS":11.5476,
  "TMT":3.4933,
  "TND":2.9186,
  "TOP":2.2871,
  "TRY":17.1656,
  "TTD":6.7643,
  "TVD":1.3887,
  "TWD":29.4166,
  "TZS":2321.1502,
  "UAH":29.4320,
  "UGX":3721.2908,
  "UYU":39.6126,
  "UZS":11032.7750,
  "VES":5.1735,
  "VND":23173.2280,
  "VUV":114.0295,
  "WST":2.6099,
  "XAF":612.0261,
  "XCD":2.7000,
  "XDR":0.7429,
  "XOF":612.0261,
  "XPF":111.3401,
  "YER":249.5075,
  "ZAR":15.3003,
  "ZMW":16.8205,
  "ZWL":297.6589
 }
}