{
 "result":"success",
 "documentation":"https://www.exchangerate-api.com/docs",
 "terms_of_use":"https://www.exchangerate-api.com/terms",
 "time_last_update_unix":1656115202,
 "time_last_update_utc":"Sat, 25 Jun 2022 00:00:02 +0000",
 "time_next_update_unix":1656201602,
 "time_next_update_utc":"Sun, 26 Jun 2022 00:00:02 +0000",
 "base_code":"USD",
 "conversion_rates":{
  "USD":1,
  "AED":3.6725,
  "AFN":89.5222,
  "ALL":113.3441,
  "AMD":408.9579,
  "ANG":1.7900,
  "AOA":430.7279,
  "ARS":123.9125,
  "AUD":1.4429,
  "AWG":1.7900,
  "AZN":1.6959,
  "BAM":1.8548,
  "BBD":2.0000,
  "BDT":91.8716,
  "BGN":1.8553,
  "BHD":0.3760,
  "BIF":2023.6539,
  "BMD":1.0000,
  "BND":1.3863,
  "BOB":6.8631,
  "BRL":5.2338,
  "BSD":1.0000,
  "BTN":78.2329,
  "BWP":12.2478,
  "BYN":2.7406,
  "BZD":2.0000,
  "CAD":1.2927,
  "CDF":1996.7603,
  "CHF":0.9581,
  "CLP":901.6722,
  "CNY":6.6932,
  "COP":4062.3703,
  "CRC":690.5391,
  "CUP":24.0000,
  "CVE":104.5699,
  "CZK":23.4407,
  "DJF":177.7210,
  "DKK":7.0751,
  "DOP":54.3795,
  "DZD":145.7323,
  "EGP":18.7554,
  "ERN":15.0000,
  "ETB":51.8982,
  "EUR":0.9484,
  "FJD":2.1985,
  "FKP":0.8158,
  "FOK":7.0751,
  "GBP":0.8158,
  "GEL":2.9327,
  "GGP":0.8158,
  "GHS":8.1395,
  "GIP":0.8158,
  "GMD":53.9886,
  "GNF":8659.3456,
  "GTQ":7.7250,
  "GYD":208.3341,
  "HKD":7.8521,
  "HNL":24.4943,
  "HRK":7.1454,
  "HTG":114.5180,
  "HUF":379.4278,
  "IDR":14815.0745,
  "ILS":3.4199,
  "IMP":0.8158,
  "INR":78.2342,
  "IQD":1453.1972,
  "IRR":42025.1129,
  "ISK":132.6245,
  "JEP":0.8158,
  "JMD":150.9545,
  "JOD":0.7090,
  "JPY":135.1699,
  "KES":117.9763,
  "KGS":80.4238,
  "KHR":4047.9068,
  "KID":1.4429,
  "KMF":466.5582,
  "KRW":1292.2545,
  "KWD":0.2996,
  "KYD":0.8333,
  "KZT":466.4936,
  "LAK":16876.1183,
  "LBP":1507.5000,
  "LKR":355.4756,
  "LRD":151.4408,
  "LSL":15.8311,
  "LYD":4.7977,
  "MAD":9.7726,
  "MDL":19.2066,
  "MGA":4047.2881,
  "MKD":58.7095,
  "MMK":1832.5823,
  "MNT":3112.2384,
  "MOP":8.0877,
  "MRU":36.1101,
  "MUR":44.7013,
  "MVR":15.3817,
  "MWK":1029.1888,
  "MXN":19.9164,
  "MYR":4.3936,
  "MZN":64.3582,
  "NAD":15.8311,
  "NGN":414.4068,
  "NIO":35.7325,
  "NOK":9.8844,
  "NPR":125.1727,
  "NZD":1.5861,
  "OMR":0.3845,
  "PAB":1.0000,
  "PEN":3.7663,
  "PGK":3.5144,
  "PHP":54.8439,
  "PKR":208.1619,
  "PLN":4.4458,
  "PYG":6897.1872,
  "QAR":3.6400,
  "RON":4.6844,
  "RSD":111.4411,
  "RUB":53.5199,
  "RWF":1058.0040,
  "SAR":3.7500,
  "SBD":7.9903,
  "SCR":13.0591,
  "SDG":467.0425,
  "SEK":10.1394,
  "SGD":1.3863,
  "SHP":0.8158,
  "SLL":13104.6477,
  "SOS":576.0848,
  "SRD":21.8087,
  "SSP":485.8952,
  "STN":23.2346,
  "SYP":2475.9834,
  "SZL":15.8311,
  "THB":35.5178,
  "TJS":11.3486,
  "TMT":3.4982,
  "TND":2.8200,
  "TOP":2.3200,
  "TRY":17.0703,
  "TTD":6.7806,
  "TVD":1.4429,
  "TWD":29.6076,
  "TZS":2330.0184,
  "UAH":29.8024,
  "UGX":3742.9242,
  "UYU":39.7082,
  "UZS":10796.2912,
  "VES":5.4688,
  "VND":23241.9244,
  "VUV":116.8640,
  "WST":2.5714,
  "XAF":622.0776,
  "XCD":2.7000,
  "XDR":0.7478,
  "XOF":622.0776,
  "XPF":113.1686,
  "YER":249.7005,
  "ZAR":15.8314,
  "ZMW":17.0442,
  "ZWL":352.8012
 }
}