{
 "result":"success",
 "documentation":"https://www.exchangerate-api.com/docs",
 "terms_of_use":"https://www.exchangerate-api.com/terms",
 "time_last_update_unix":1646784001,
 "time_last_update_utc":"Wed, 09 Mar 2022 00:00:01 +0000",
 "time_next_update_unix":1646870401,
 "time_next_update_utc":"Thu, 10 Mar 2022 00:00:01 +0000",
 "base_code":"USD",
 "conversion_rates":{
  "USD":1,
  "AED":3.6725,
  "AFN":89.5392,
  "ALL":115.3135,
  "AMD":509.6537,
  "ANG":1.7900,
  "AOA":479.4481,
  "ARS":108.3757,
  "AUD":1.3735,
  "AWG":1.7900,
  "AZN":1.6976,
  "BAM":1.7954,
  "BBD":2.0000,
  "BDT":85.1712,
  "BGN":1.7954,
  "BHD":0.3760,
  "BIF":2000.4027,
  "BMD":1.0000,
  "BND":1.3638,
  "BOB":6.8651,
  "BRL":5.0858,
  "BSD":1.0000,
  "BTN":76.9022,
  "BWP":11.7258,
  "BYN":2.9597,
  "BZD":2.0000,
  "CAD":1.2856,
  "CDF":1992.2513,
  "CHF":0.9290,
  "CLP":811.3757,
  "CNY":6.3204,
  "COP":3834.1090,
  "CRC":648.5718,
  "CUP":24.0000,
  "CVE":101.2177,
  "CZK":23.4587,
  "DJF":177.7210,
  "DKK":6.8483,
  "DOP":54.9529,
  "DZD":142.9118,
  "EGP":15.7097,
  "ERN":15.0000,
  "ETB":51.2945,
  "EUR":0.9181,
  "FJD":2.1069,
  "FKP":0.7631,
  "FOK":6.8483,
  "GBP":0.7631,
  "GEL":3.4126,
  "GGP":0.7631,
  "GHS":7.7309,
  "GIP":0.7631,
  "GMD":52.9950,
  "GNF":8916.7947,
  "GTQ":7.6908,
  "GYD":207.7281,
  "HKD":7.8223,
  "HNL":24.4557,
  "HRK":6.9163,
  "HTG":106.0045,
  "HUF":357.0747,
  "IDR":14319.3711,
  "ILS":3.3010,
  "IMP":0.7631,
  "INR":76.9046,
  "IQD":1449.0543,
  "IRR":42154.3170,
  "ISK":134.0550,
  "JEP":0.7631,
  "JMD":153.8283,
  "JOD":0.7090,
  "JPY":115.6658,
  "KES":114.3079,
  "KGS":94.9534,
  "KHR":4035.5822,
  "KID":1.3735,
  "KMF":451.6014,
  "KRW":1231.2706,
  "KWD":0.2996,
  "KYD":0.8333,
  "KZT":509.0040,
  "LAK":12434.2343,
  "LBP":1507.5000,
  "LKR":221.3925,
  "LRD":153.8333,
  "LSL":15.2878,
  "LYD":4.5751,
  "MAD":9.5607,
  "MDL":18.3243,
  "MGA":3034.8678,
  "MKD":56.6133,
  "MMK":1764.9736,
  "MNT":2865.2634,
  "MOP":8.0569,
  "MRU":36.1168,
  "MUR":43.8565,
  "MVR":15.3955,
  "MWK":820.4038,
  "MXN":21.3758,
  "MYR":4.1722,
  "MZN":63.8613,
  "NAD":15.2878,
  "NGN":414.7944,
  "NIO":36.0154,
  "NOK":8.9921,
  "NPR":123.0435,
  "NZD":1.4677,
  "OMR":0.3845,
  "PAB":1.0000,
  "PEN":3.7317,
  "PGK":3.5184,
  "PHP":52.2993,
  "PKR":178.4599,
  "PLN":4.5063,
  "PYG":6835.4036,
  "QAR":3.6400,
  "RON":4.5304,
  "RSD":108.0990,
  "RUB":132.2693,
  "RWF":1048.3007,
  "SAR":3.7500,
  "SBD":8.0053,
  "SCR":14.3648,
  "SDG":444.3709,
  "SEK":9.9547,
  "SGD":1.3639,
  "SHP":0.7631,
  "SLL":11553.4813,
  "SOS":574.3545,
  "SRD":20.3210,
  "SSP":430.2712,
  "STN":22.4898,
  "SYP":2510.9209,
  "SZL":15.2878,
  "THB":33.1828,
  "TJS":11.2659,
  "TMT":3.4705,
  "TND":2.7806,
  "TOP":2.2373,
  "TRY":14.4949,
  "TTD":6.7590,
  "TVD":1.3735,
  "TWD":28.2622,
  "TZS":2316.9606,
  "UAH":31.3700,
  "UGX":3614.0218,
  "UYU":42.6039,
  "UZS":10853.6945,
  "VES":4.3250,
  "VND":22843.1769,
  "VUV":112.6606,
  "WST":2.5591,
  "XAF":602.1352,
  "XCD":2.7000,
  "XDR":0.7246,
  "XOF":602.1352,
  "XPF":109.5407,
  "YER":249.9778,
  "ZAR":15.2906,
  "ZMW":18.0542,
  "ZWL":127.4504
 }
}